setup.py
pytg/__init__.py
pytg/argument_types.py
pytg/exceptions.py
pytg/fix_msg_array.py
pytg/fix_plain_output.py
pytg/receiver.py
pytg/result_parser.py
pytg/sender.py
pytg/test.py
pytg/this_py_version.py
pytg/utils.py
pytg.egg-info/PKG-INFO
pytg.egg-info/SOURCES.txt
pytg.egg-info/dependency_links.txt
pytg.egg-info/requires.txt
pytg.egg-info/top_level.txt