Metadata-Version: 1.1
Name: pytg
Version: 0.4.7
Summary: Connect to the Telegram CLI, receive and send Telegram messages.
Home-page: https://github.com/luckydonald/pytg
Author: luckydonald
Author-email: code@luckydonald.de
License: GPLv3+
Keywords: telegram cli python message send receive python secure fast answer reply image voice picture location contacts typing multi messanger
Platform: UNKNOWN
Classifier: Development Status :: 4 - Beta
Classifier: Intended Audience :: Developers
Classifier: Topic :: Software Development :: Build Tools
Classifier: License :: OSI Approved :: GNU General Public License v3 or later (GPLv3+)
Classifier: Programming Language :: Python :: 2.7
Classifier: Programming Language :: Python :: 3.4
Classifier: Operating System :: MacOS :: MacOS X
Classifier: Operating System :: Unix
Classifier: Programming Language :: Python
Classifier: Programming Language :: Python :: 3.4
Classifier: Programming Language :: Python :: 3
Classifier: Topic :: Communications
Classifier: Topic :: Communications :: Chat
Classifier: Topic :: Software Development :: Libraries
